noahs_image_classifier/__init__.py
noahs_image_classifier/classify.py
noahs_image_classifier-0.1.0.dist-info/METADATA
noahs_image_classifier-0.1.0.dist-info/WHEEL
noahs_image_classifier-0.1.0.dist-info/top_level.txt
noahs_image_classifier-0.1.0.dist-info/RECORD
