Metadata-Version: 2.4
Name: noahs_image_classifier
Version: 0.1.0
Summary: A very basic and easy to use module for images classification. Works on any Mac OS, Windows and Linux but is intended to be used on Raspberry Pi or similar edge device
Author-email: Noah Jones <jonesnoah45010@gmail.com>
License: MIT
Project-URL: GitHub, https://github.com/jonesnoah45010/image_classifier
Classifier: Programming Language :: Python :: 3
Classifier: Operating System :: OS Independent
Classifier: License :: OSI Approved :: MIT License
Classifier: Intended Audience :: Developers
Classifier: Environment :: Console
Classifier: Topic :: Software Development :: Libraries :: Python Modules
Requires-Python: >=3.9
Requires-Dist: numpy<=1.24.4
Requires-Dist: pillow
Requires-Dist: tensorflow; sys_platform == "darwin"
Requires-Dist: tflite-runtime==2.13.0; sys_platform == "linux"
Requires-Dist: noahs_camera_controller
